supermarket_connector/__init__.py
supermarket_connector/enums.py
supermarket_connector/models/__init__.py
supermarket_connector/models/category/__init__.py
supermarket_connector/models/image/__init__.py
supermarket_connector/models/product/__init__.py
supermarket_connector/nl/__init__.py
supermarket_connector/nl/albert_heijn/__init__.py
supermarket_connector/nl/albert_heijn/client.py
supermarket_connector/nl/albert_heijn/errors.py
supermarket_connector/nl/aldi/__init__.py
supermarket_connector/nl/jumbo/__init__.py
supermarket_connector/nl/jumbo/client.py
supermarket_connector/nl/jumbo/errors.py
supermarket_connector/nl/picnic/__init__.py
supermarket_connector/nl/picnic/client.py
supermarket_connector/nl/picnic/errors.py
supermarket_connector/utils/__init__.py
supermarket_connector-0.0.14.dist-info/LICENSE
supermarket_connector-0.0.14.dist-info/METADATA
supermarket_connector-0.0.14.dist-info/WHEEL
supermarket_connector-0.0.14.dist-info/top_level.txt
supermarket_connector-0.0.14.dist-info/RECORD
