Metadata-Version: 2.1
Name: supermarket-connector
Version: 0.0.14
Summary: Supermarket Mobile API Connector
Home-page: https://github.com/Repsay/supermarket-mobile-api-connector
Author: Jasper Delahaije
Author-email: jdelahaije@gmail.com
License: MIT
Download-URL: https://github.com/Repsay/supermarket-mobile-api-connector/releases
Platform: UNKNOWN
Classifier: Development Status :: 2 - Pre-Alpha
Classifier: Intended Audience :: Developers
Classifier: Topic :: Software Development :: Libraries :: Python Modules
Classifier: Topic :: Utilities
Classifier: License :: OSI Approved :: MIT License
Classifier: Programming Language :: Python :: 3.8
Classifier: Programming Language :: Python :: 3.9
Classifier: Programming Language :: Python :: 3.10
Classifier: Natural Language :: English
Classifier: Natural Language :: Dutch
Requires-Python: >=3.8
License-File: LICENSE
Requires-Dist: requests
Requires-Dist: unidecode
Requires-Dist: free-proxy
